code_analysis/__init__.py
code_analysis/java_call_tree.py
code_analysis/java_dependencies.py
code_analysis/python_dependencies.py
code_analysis-0.1.5.dist-info/LICENSE
code_analysis-0.1.5.dist-info/METADATA
code_analysis-0.1.5.dist-info/WHEEL
code_analysis-0.1.5.dist-info/entry_points.txt
code_analysis-0.1.5.dist-info/top_level.txt
code_analysis-0.1.5.dist-info/RECORD
