Metadata-Version: 2.1
Name: code-analysis
Version: 0.1.5
Summary: Analyze source code dependencies and call trees in Neo4j.
Home-page: https://github.com/stbraun/code_analysis
Author: Stefan Braun
Author-email: sb@stbraun.com
License: MIT license
Keywords: code_analysis
Platform: UNKNOWN
Classifier: Development Status :: 2 - Pre-Alpha
Classifier: Intended Audience :: Developers
Classifier: License :: OSI Approved :: MIT License
Classifier: Natural Language :: English
Classifier: Programming Language :: Python :: 3
Classifier: Programming Language :: Python :: 3.7
Classifier: Programming Language :: Python :: 3.8
Requires-Dist: Click (>=6.0)
